Metadata-Version: 2.1
Name: hwm93
Version: 0.9.1
Summary: Horizontal Wind Model 1993 in Python
Home-page: https://github.com/scivision/hwm93
Author: Michael Hirsch, Ph.D.
License: UNKNOWN
Keywords: mesosphere,stratosphere,thermosphere
Platform: UNKNOWN
Classifier: Development Status :: 4 - Beta
Classifier: Environment :: Console
Classifier: Intended Audience :: Science/Research
Classifier: License :: OSI Approved :: MIT License
Classifier: Operating System :: OS Independent
Classifier: Programming Language :: Fortran
Classifier: Programming Language :: Python :: 3.6
Classifier: Programming Language :: Python :: 3.7
Classifier: Topic :: Scientific/Engineering :: Atmospheric Science
Requires-Python: >= 3.6
Provides-Extra: plot
Provides-Extra: tests
